LICENSE
README.md
pyproject.toml
setup.py
src/__init__.py
src/sagemaker_kernel_wrapper/__init__.py
src/sagemaker_kernel_wrapper/client.py
src/sagemaker_kernel_wrapper/metadata.py
src/sagemaker_kernel_wrapper/resource_tag.py
src/sagemaker_kernel_wrapper/sm_gis_wrapper.py
src/sagemaker_kernel_wrapper.egg-info/PKG-INFO
src/sagemaker_kernel_wrapper.egg-info/SOURCES.txt
src/sagemaker_kernel_wrapper.egg-info/dependency_links.txt
src/sagemaker_kernel_wrapper.egg-info/requires.txt
src/sagemaker_kernel_wrapper.egg-info/top_level.txt
test/test_app_metadata.py
test/test_client.py
test/test_internal_metadata.py
test/test_resource_tag.py
test/test_sm_gis_wrapper.py