Metadata-Version: 2.4
Name: sagemaker-kernel-wrapper
Version: 0.0.6
Summary: SageMaker Kernel Wrapper Package
Author: Amazon Web Services
License: 
Project-URL: homepage, https://aws.amazon.com/sagemaker
Classifier: Intended Audience :: Developers
Classifier: Intended Audience :: Science/Research
Classifier: License :: OSI Approved :: Apache Software License
Classifier: Programming Language :: Python
Classifier: Programming Language :: Python :: 3.8
Classifier: Programming Language :: Python :: 3.9
Classifier: Programming Language :: Python :: 3.10
Classifier: Programming Language :: Python :: 3.11
Requires-Python: >=3.8
License-File: LICENSE
Requires-Dist: boto3
Provides-Extra: dev
Requires-Dist: black; extra == "dev"
Requires-Dist: build; extra == "dev"
Provides-Extra: test
Requires-Dist: pytest; extra == "test"
Requires-Dist: parameterized; extra == "test"
Dynamic: license-file
